copy_progress/__init__.py
copy_progress/copy.py
copy_progress-0.1.3.dist-info/METADATA
copy_progress-0.1.3.dist-info/WHEEL
copy_progress-0.1.3.dist-info/LICENSE
copy_progress-0.1.3.dist-info/entry_points.txt
copy_progress-0.1.3.dist-info/RECORD
